tesseral/__init__.py
tesseral/access_tokens.py
tesseral/api_key_role_assignments/__init__.py
tesseral/api_key_role_assignments/client.py
tesseral/api_keys/__init__.py
tesseral/api_keys/client.py
tesseral/audit_log_events/__init__.py
tesseral/audit_log_events/client.py
tesseral/client.py
tesseral/core/__init__.py
tesseral/core/api_error.py
tesseral/core/client_wrapper.py
tesseral/core/datetime_utils.py
tesseral/core/file.py
tesseral/core/http_client.py
tesseral/core/jsonable_encoder.py
tesseral/core/pydantic_utilities.py
tesseral/core/query_encoder.py
tesseral/core/remove_none_from_dict.py
tesseral/core/request_options.py
tesseral/core/serialization.py
tesseral/environment.py
tesseral/errors/__init__.py
tesseral/errors/bad_request_error.py
tesseral/errors/forbidden_error.py
tesseral/errors/not_found_error.py
tesseral/errors/unauthorized_error.py
tesseral/oidc_connections/__init__.py
tesseral/oidc_connections/client.py
tesseral/organizations/__init__.py
tesseral/organizations/client.py
tesseral/passkeys/__init__.py
tesseral/passkeys/client.py
tesseral/projects/__init__.py
tesseral/projects/client.py
tesseral/py.typed
tesseral/roles/__init__.py
tesseral/roles/client.py
tesseral/saml_connections/__init__.py
tesseral/saml_connections/client.py
tesseral/scim_api_keys/__init__.py
tesseral/scim_api_keys/client.py
tesseral/sessions/__init__.py
tesseral/sessions/client.py
tesseral/types/__init__.py
tesseral/types/access_token_claims.py
tesseral/types/access_token_impersonator.py
tesseral/types/access_token_organization.py
tesseral/types/access_token_session.py
tesseral/types/access_token_user.py
tesseral/types/api_error.py
tesseral/types/api_key.py
tesseral/types/api_key_role_assignment.py
tesseral/types/audit_log_event.py
tesseral/types/authenticate_api_key_response.py
tesseral/types/create_api_key_response.py
tesseral/types/create_api_key_role_assignment_response.py
tesseral/types/create_audit_log_event_response.py
tesseral/types/create_oidc_connection_response.py
tesseral_sdk-0.0.12.dist-info/LICENSE
tesseral_sdk-0.0.12.dist-info/METADATA
tesseral_sdk-0.0.12.dist-info/WHEEL
tesseral_sdk-0.0.12.dist-info/RECORD
